LICENSE
README.md
setup.py
Dgram.egg-info/PKG-INFO
Dgram.egg-info/SOURCES.txt
Dgram.egg-info/dependency_links.txt
Dgram.egg-info/requires.txt
Dgram.egg-info/top_level.txt
dgram/__init__.py
dgram/apihelper.py
dgram/async_telebot.py
dgram/asyncio_filters.py
dgram/asyncio_handler_backends.py
dgram/asyncio_helper.py
dgram/callback_data.py
dgram/custom_filters.py
dgram/formatting.py
dgram/handler_backends.py
dgram/types.py
dgram/util.py
dgram/version.py
dgram/asyncio_storage/__init__.py
dgram/asyncio_storage/base_storage.py
dgram/asyncio_storage/memory_storage.py
dgram/asyncio_storage/pickle_storage.py
dgram/asyncio_storage/redis_storage.py
dgram/ext/__init__.py
dgram/ext/reloader.py
dgram/ext/aio/__init__.py
dgram/ext/aio/webhooks.py
dgram/ext/sync/__init__.py
dgram/ext/sync/webhooks.py
dgram/storage/__init__.py
dgram/storage/base_storage.py
dgram/storage/memory_storage.py
dgram/storage/pickle_storage.py
dgram/storage/redis_storage.py