Metadata-Version: 2.1
Name: Dgram
Version: 1.0.0
Summary: Python Telegram bot api. 
Home-page: https://github.com/DEV-Degram/Dgram
Author: - Team Zero
Author-email: degram27@gmail.com
License: GPL2
Keywords: telegram bot api tools
Platform: UNKNOWN
Classifier: Development Status :: 5 - Production/Stable
Classifier: Programming Language :: Python :: 3
Classifier: Environment :: Console
Classifier: License :: OSI Approved :: GNU General Public License v2 (GPLv2)
Provides-Extra: json
Provides-Extra: PIL
Provides-Extra: redis
Provides-Extra: aioredis
Provides-Extra: aiohttp
Provides-Extra: fastapi
Provides-Extra: uvicorn
Provides-Extra: psutil
Provides-Extra: coloredlogs
Provides-Extra: watchdog
License-File: LICENSE
